setup.cfg
setup.py
hug_peewee/__init__.py
hug_peewee/_version.py
hug_peewee/connection.py
hug_peewee.egg-info/PKG-INFO
hug_peewee.egg-info/SOURCES.txt
hug_peewee.egg-info/dependency_links.txt
hug_peewee.egg-info/requires.txt
hug_peewee.egg-info/top_level.txt