Metadata-Version: 1.1
Name: hug-peewee
Version: 0.0.2
Summary: An extension to hug that adds clean integration with the peewee ORM
Home-page: https://github.com/timothycrosley/hug_peewee
Author: Timothy Crosley
Author-email: timothy.crosley@gmail.com
License: MIT
Keywords: Python,Python3
Platform: UNKNOWN
Classifier: Development Status :: 6 - Mature
Classifier: Intended Audience :: Developers
Classifier: Natural Language :: English
Classifier: Environment :: Console
Classifier: License :: OSI Approved :: MIT License
Classifier: Programming Language :: Python
Classifier: Programming Language :: Python :: 3
Classifier: Programming Language :: Python :: 3.2
Classifier: Programming Language :: Python :: 3.3
Classifier: Programming Language :: Python :: 3.4
Classifier: Programming Language :: Python :: 3.5
Classifier: Topic :: Software Development :: Libraries
Classifier: Topic :: Utilities
Requires: hug
Requires: peewee
